mohcalc/__init__.py
mohcalc-0.1.dist-info/LICENSE.txt
mohcalc-0.1.dist-info/METADATA
mohcalc-0.1.dist-info/WHEEL
mohcalc-0.1.dist-info/top_level.txt
mohcalc-0.1.dist-info/RECORD
