Metadata-Version: 2.1
Name: mohcalc
Version: 0.1
Summary: Basic Calculator
Home-page: UNKNOWN
Author: Mohamad Elsadek
Author-email: moh.elsadek@hotmail.com
License: UNKNOWN
Platform: UNKNOWN
Classifier: Programming Language :: Python :: 3.8
Classifier: License :: OSI Approved :: MIT License
Classifier: Operating System :: OS Independent
License-File: LICENSE.txt
